{
  "project_info": {
    "project_number": "485286052876",
    "project_id": "tablextract-authentication",
    "storage_bucket": "tablextract-authentication.appspot.com"
  },
  "client": [
    {
      "client_info": {
        "mobilesdk_app_id": "1:485286052876:android:0c7cc7d537cd1d91441a29",
        "android_client_info": {
          "package_name": "Tablextract.Application"
        }
      },
      "oauth_client": [
        {
          "client_id": "485286052876-b70ipav25j5pnprj93crs9govuf1i3bf.apps.googleusercontent.com",
          "client_type": 3
        }
      ],
      "api_key": [
        {
          "current_key": "AIzaSyDzqFOVpKdQ9B0mm7liAYJrpiywoJAtc_E"
        }
      ],
      "services": {
        "appinvite_service": {
          "other_platform_oauth_client": [
            {
              "client_id": "485286052876-b70ipav25j5pnprj93crs9govuf1i3bf.apps.googleusercontent.com",
              "client_type": 3
            }
          ]
        }
      }
    }
  ],
  "configuration_version": "1"
}